{
  "candidate": {
    "address": "0x1a9b68ca1dcacb106c4b853e2d9c915f0cfe2e56",
    "category": "fresh contract",
    "chain": "bsc",
    "entity_type": "unknown_protocol",
    "external_id": "bsc:0x1a9b68ca1dcacb106c4b853e2d9c915f0cfe2e56",
    "name": "0x1a9b68ca1dcacb106c4b853e2d9c915f0cfe2e56",
    "source": "bsc_chain_scanner",
    "url": "https://bscscan.com/address/0x1a9b68ca1dcacb106c4b853e2d9c915f0cfe2e56"
  },
  "deepwiki_focus": {
    "gate_question": "Does this exact current protocol, with current live state, allow an unprivileged attacker to extract funds or rewards beyond entitlement?",
    "local_questions": [
      "What exact live contract holds or controls the funds/rewards?",
      "Which public selectors can move, mint, claim, redeem, release, or sweep value?",
      "Can an unprivileged caller gain more than their entitlement?"
    ],
    "proof_route": "recon_bravo_then_corecritical",
    "why_this_candidate_matters": "Candidate has live value at risk near $1,932,106 and matches Sentinel fund/reward extraction surfaces."
  },
  "live_evidence": {
    "deployer_address": "",
    "funding_cluster_id": "",
    "tags": [
      "audit_hidden_contract",
      "balance_spike",
      "fresh_contract_large_balance",
      "fresh_contract_large_token_balance",
      "hidden_high_value_contract",
      "high_token_balance",
      "high_total_balance",
      "immediate_balance_spike",
      "known_asset_balance",
      "stablecoin_balance",
      "token_funded_contract",
      "unfamiliar_contract",
      "unknown_protocol",
      "unknown_verification_status"
    ],
    "verified_source": null
  },
  "rank": 12,
  "raw_scored_row": {
    "address": "0x1a9b68ca1dcacb106c4b853e2d9c915f0cfe2e56",
    "category": "fresh contract",
    "chain": "bsc",
    "created_at_ms": null,
    "deployer_address": "",
    "entity_type": "unknown_protocol",
    "external_id": "bsc:0x1a9b68ca1dcacb106c4b853e2d9c915f0cfe2e56",
    "fdv_usd": 0.0,
    "funding_cluster_id": "",
    "liquidity_usd": 0.0,
    "name": "0x1a9b68ca1dcacb106c4b853e2d9c915f0cfe2e56",
    "next_action": "recon_bravo_then_corecritical",
    "price_change_24h_pct": 0.0,
    "reasons": [
      "value_at_risk>=1000000:1932106",
      "chain_weight:bsc:10",
      "unknown_protocol:10",
      "unfamiliar_contract:12",
      "unknown_verification_status:8",
      "hidden_high_value_contract:18",
      "balance_spike:20"
    ],
    "score": 103,
    "source": "bsc_chain_scanner",
    "tags": [
      "audit_hidden_contract",
      "balance_spike",
      "fresh_contract_large_balance",
      "fresh_contract_large_token_balance",
      "hidden_high_value_contract",
      "high_token_balance",
      "high_total_balance",
      "immediate_balance_spike",
      "known_asset_balance",
      "stablecoin_balance",
      "token_funded_contract",
      "unfamiliar_contract",
      "unknown_protocol",
      "unknown_verification_status"
    ],
    "tvl_usd": 1932105.5716429413,
    "url": "https://bscscan.com/address/0x1a9b68ca1dcacb106c4b853e2d9c915f0cfe2e56",
    "verified_source": null,
    "volume24h_usd": 0.0
  },
  "schema_version": "sentinel-candidate-brief-v1",
  "score": {
    "next_action": "recon_bravo_then_corecritical",
    "reasons": [
      "value_at_risk>=1000000:1932106",
      "chain_weight:bsc:10",
      "unknown_protocol:10",
      "unfamiliar_contract:12",
      "unknown_verification_status:8",
      "hidden_high_value_contract:18",
      "balance_spike:20"
    ],
    "value": 103
  },
  "value_at_risk": {
    "fdv_usd": 0.0,
    "liquidity_usd": 0.0,
    "price_change_24h_pct": 0.0,
    "tvl_usd": 1932105.5716429413,
    "usd": 1932105.5716429413,
    "volume24h_usd": 0.0
  }
}
